sdfspu/__init__.py
sdfspu/csv_data.py
sdfspu/ini_config.py
sdfspu/sdf_net.py
sdfspu/sdf_text.py
sdfspu/sdf_time.py
sdfspu-0.2.4.dist-info/LICENSE
sdfspu-0.2.4.dist-info/METADATA
sdfspu-0.2.4.dist-info/WHEEL
sdfspu-0.2.4.dist-info/top_level.txt
sdfspu-0.2.4.dist-info/RECORD
