Metadata-Version: 2.1
Name: sdfspu
Version: 0.2.4
Summary: Some Python Utilities, by sdf
Home-page: https://github.com/soundmaking/sdfspu
Download-URL: https://github.com/soundmaking/sdfspu/archive/refs/heads/main.zip
Author: Samuel Freeman
Author-email: soundmaking@merfasmean.com
License: MIT
Classifier: Development Status :: 2 - Pre-Alpha
Classifier: Intended Audience :: Developers
Classifier: Topic :: Software Development
Classifier: License :: OSI Approved :: MIT License
Classifier: Operating System :: OS Independent
Classifier: Programming Language :: Python :: 3.7
License-File: LICENSE
Requires-Dist: requests
